flake8_import_relative_two/__init__.py
flake8_import_relative_two/core.py
flake8_import_relative_two/version.py
flake8_import_relative_two-0.2.0.dist-info/LICENSE
flake8_import_relative_two-0.2.0.dist-info/METADATA
flake8_import_relative_two-0.2.0.dist-info/WHEEL
flake8_import_relative_two-0.2.0.dist-info/entry_points.txt
flake8_import_relative_two-0.2.0.dist-info/RECORD
