Metadata-Version: 2.1
Name: flake8-import-relative-two
Version: 0.2.0
Summary: Flake8 plugin that checks for relative imports up to a maximum of level two
Home-page: https://github.com/bartoszcholewa/flake8-import-relative-two
License: MIT
Keywords: flake8-plugin,linting,absolute-imports,relative-imports
Author: Bartosz Cholewa
Author-email: bbcholewa@gmail.com
Requires-Python: >=3.10,<4.0
Classifier: Development Status :: 5 - Production/Stable
Classifier: Framework :: Flake8
Classifier: Intended Audience :: Developers
Classifier: License :: OSI Approved
Classifier: License :: OSI Approved :: MIT License
Classifier: Natural Language :: English
Classifier: Operating System :: OS Independent
Classifier: Programming Language :: Python
Classifier: Programming Language :: Python :: 3
Classifier: Programming Language :: Python :: 3.10
Classifier: Programming Language :: Python :: 3.11
Classifier: Programming Language :: Python :: 3 :: Only
Classifier: Programming Language :: Python :: 3.12
Classifier: Programming Language :: Python :: 3.8
Classifier: Programming Language :: Python :: 3.9
Classifier: Topic :: Software Development :: Quality Assurance
Requires-Dist: flake8 (>=6.0.0,<7.0.0)
Project-URL: Repository, https://github.com/bartoszcholewa/flake8-import-relative-two
